{
    "pilotes": [
        {
            "prenom": "Max",
            "nom": "Verstappen",
            "numero_pilote": 33,
            "nombre_de_victoires": 56,
            "equipe": "Red Bull Racing",
            "pays_origine": "Netherlands",
            "nb_podiums": 100,
            "points_totaux": 2637.5,
            "grands_prix_effectues": 187,
            "nombre_de_coupes_du_monde": 3,
            "meilleur_place": 1,
            "date_de_naissance": "1997-09-30",
            "casques": "/data/img/casques/verstappen.png",
            "photo": "/data/img/pilotes/verstappen.png"
        },
        {
            "prenom": "Sergio",
            "nom": "Perez",
            "numero_pilote": 11,
            "nombre_de_victoires": 6,
            "equipe": "Red Bull Racing",
            "pays_origine": "Mexico",
            "nb_podiums": 37,
            "points_totaux": 1522,
            "grands_prix_effectues": 260,
            "nombre_de_coupes_du_monde": 0,
            "meilleur_place": 1,
            "date_de_naissance": "1990-01-26",
            "casques": "/data/img/casques/perez.png",
            "photo": "/data/img/pilotes/perez.png"
        },
        {
            "prenom": "Charles",
            "nom": "Leclerc",
            "numero_pilote": 16,
            "nombre_de_victoires": 5,
            "equipe": "Ferrari",
            "pays_origine": "Monaco",
            "nb_podiums": 31,
            "points_totaux": 1102,
            "grands_prix_effectues": 127,
            "nombre_de_coupes_du_monde": 0,
            "meilleur_place": 1,
            "date_de_naissance": "1997-10-16",
            "casques": "/data/img/casques/leclerc.png",
            "photo": "/data/img/pilotes/leclerc.png"
        },
        {
            "prenom": "George",
            "nom": "Russell",
            "numero_pilote": 63,
            "nombre_de_victoires": 1,
            "equipe": "Mercedes",
            "pays_origine": "United Kingdom",
            "nb_podiums": 11,
            "points_totaux": 487,
            "grands_prix_effectues": 106,
            "nombre_de_coupes_du_monde": 0,
            "meilleur_place": 1,
            "date_de_naissance": "1998-02-15",
            "casques": "/data/img/casques/russell.png",
            "photo": "/data/img/pilotes/russell.png"
        },
        {
            "prenom": "Oscar",
            "nom": "Piastri",
            "numero_pilote": 81,
            "nombre_de_victoires": 0,
            "equipe": "McLaren",
            "pays_origine": "Australia",
            "nb_podiums": 2,
            "points_totaux": 113,
            "grands_prix_effectues": 24,
            "nombre_de_coupes_du_monde": 0,
            "meilleur_place": 2,
            "date_de_naissance": "2001-04-06",
            "casques": "/data/img/casques/piastri.png",
            "photo": "/data/img/pilotes/piastri.png"
        },
        {
            "prenom": "Carlos",
            "nom": "Sainz",
            "numero_pilote": 55,
            "nombre_de_victoires": 2,
            "equipe": "Ferrari",
            "pays_origine": "Spain",
            "nb_podiums": 19,
            "points_totaux": 997.5,
            "grands_prix_effectues": 186,
            "nombre_de_coupes_du_monde": 0,
            "meilleur_place": 2,
            "date_de_naissance": "1994-09-01",
            "casques": "/data/img/casques/sainz.png",
            "photo": "/data/img/pilotes/sainz.png"
        },
        {
            "prenom": "Fernando",
            "nom": "Alonso",
            "numero_pilote": 14,
            "nombre_de_victoires": 32,
            "equipe": "Aston Martin",
            "pays_origine": "Spain",
            "nb_podiums": 106,
            "points_totaux": 2279,
            "grands_prix_effectues": 382,
            "nombre_de_coupes_du_monde": 2,
            "meilleur_place": 1,
            "date_de_naissance": "1981-07-29",
            "casques": "/data/img/casques/alonso.png",
            "photo": "/data/img/pilotes/alonso.png"
        },
        {
            "prenom": "Lando",
            "nom": "Norris",
            "numero_pilote": 4,
            "nombre_de_victoires": 0,
            "equipe": "McLaren",
            "pays_origine": "United Kingdom",
            "nb_podiums": 13,
            "points_totaux": 645,
            "grands_prix_effectues": 106,
            "nombre_de_coupes_du_monde": 0,
            "meilleur_place": 2,
            "date_de_naissance": "1999-11-13",
            "casques": "/data/img/casques/norris.png",
            "photo": "/data/img/pilotes/norris.png"
        },
        {
            "prenom": "Lewis",
            "nom": "Hamilton",
            "numero_pilote": 44,
            "nombre_de_victoires": 103,
            "equipe": "Mercedes",
            "pays_origine": "United Kingdom",
            "nb_podiums": 197,
            "points_totaux": 4647.5,
            "grands_prix_effectues": 334,
            "nombre_de_coupes_du_monde": 7,
            "meilleur_place": 1,
            "date_de_naissance": "1985-01-07",
            "casques": "/data/img/casques/hamilton.png",
            "photo": "/data/img/pilotes/hamilton.png"
        },
        {
            "prenom": "Nico",
            "nom": "Hulkenberg",
            "numero_pilote": 27,
            "nombre_de_victoires": 0,
            "equipe": "Haas F1 Team",
            "pays_origine": "Germany",
            "nb_podiums": 0,
            "points_totaux": 531,
            "grands_prix_effectues": 208,
            "nombre_de_coupes_du_monde": 0,
            "meilleur_place": 4,
            "date_de_naissance": "1987-08-19",
            "casques": "/data/img/casques/hulkenberg.png",
            "photo": "/data/img/pilotes/hulkenberg.png"
        },
        {
            "prenom": "Lance",
            "nom": "Stroll",
            "numero_pilote": 18,
            "nombre_de_victoires": 0,
            "equipe": "Aston Martin",
            "pays_origine": "Canada",
            "nb_podiums": 3,
            "points_totaux": 269,
            "grands_prix_effectues": 145,
            "nombre_de_coupes_du_monde": 0,
            "meilleur_place": 3,
            "date_de_naissance": "1998-10-29",
            "casques": "/data/img/casques/stroll.png",
            "photo": "/data/img/pilotes/stroll.png"
        },
        {
            "prenom": "Alexander",
            "nom": "Albon",
            "numero_pilote": 23,
            "nombre_de_victoires": 0,
            "equipe": "Williams",
            "pays_origine": "Thailand",
            "nb_podiums": 2,
            "points_totaux": 228,
            "grands_prix_effectues": 83,
            "nombre_de_coupes_du_monde": 0,
            "meilleur_place": 3,
            "date_de_naissance": "1996-03-23",
            "casques": "/data/img/casques/albon.png",
            "photo": "/data/img/pilotes/albon.png"
        },
        {
            "prenom": "Zhou",
            "nom": "Guanyu",
            "numero_pilote": 24,
            "nombre_de_victoires": 0,
            "equipe": "Kick Sauber",
            "pays_origine": "China",
            "nb_podiums": 0,
            "points_totaux": 12,
            "grands_prix_effectues": 46,
            "nombre_de_coupes_du_monde": 0,
            "meilleur_place": 8,
            "date_de_naissance": "1999-05-30",
            "casques": "/data/img/casques/zhou.png",
            "photo": "/data/img/pilotes/zhou.png"
        },
        {
            "prenom": "Kevin",
            "nom": "Magnussen",
            "numero_pilote": 20,
            "nombre_de_victoires": 0,
            "equipe": "Haas F1 Team",
            "pays_origine": "Denmark",
            "nb_podiums": 1,
            "points_totaux": 186,
            "grands_prix_effectues": 166,
            "nombre_de_coupes_du_monde": 0,
            "meilleur_place": 2,
            "date_de_naissance": "1992-10-05",
            "casques": "/data/img/casques/magnussen.png",
            "photo": "/data/img/pilotes/magnussen.png"
        },
        {
            "prenom": "Daniel",
            "nom": "Ricciardo",
            "numero_pilote": 3,
            "nombre_de_victoires": 8,
            "equipe": "RB",
            "pays_origine": "Australia",
            "nb_podiums": 32,
            "points_totaux": 1317,
            "grands_prix_effectues": 241,
            "nombre_de_coupes_du_monde": 0,
            "meilleur_place": 1,
            "date_de_naissance": "1989-07-01",
            "casques": "/data/img/casques/ricciardo.png",
            "photo": "/data/img/pilotes/ricciardo.png"
        },
        {
            "prenom": "Esteban",
            "nom": "Ocon",
            "numero_pilote": 31,
            "nombre_de_victoires": 1,
            "equipe": "Renault",
            "pays_origine": "France",
            "nb_podiums": 3,
            "points_totaux": 422,
            "grands_prix_effectues": 135,
            "nombre_de_coupes_du_monde": 0,
            "meilleur_place": 1,
            "date_de_naissance": "1996-09-17",
            "casques": "/data/img/casques/ocon.png",
            "photo": "/data/img/pilotes/ocon.png"
        },
        {
            "prenom": "Yuki",
            "nom": "Tsunoda",
            "numero_pilote": 22,
            "nombre_de_victoires": 0,
            "equipe": "RB",
            "pays_origine": "Japan",
            "nb_podiums": 0,
            "points_totaux": 61,
            "grands_prix_effectues": 68,
            "nombre_de_coupes_du_monde": 0,
            "meilleur_place": 4,
            "date_de_naissance": "2000-05-11",
            "casques": "/data/img/casques/tsunoda.png",
            "photo": "/data/img/pilotes/tsunoda.png"
        },
        {
            "prenom": "Logan",
            "nom": "Sargeant",
            "numero_pilote": 2,
            "nombre_de_victoires": 0,
            "equipe": "Williams",
            "pays_origine": "United States of America",
            "nb_podiums": 0,
            "points_totaux": 1,
            "grands_prix_effectues": 24,
            "nombre_de_coupes_du_monde": 0,
            "meilleur_place": 10,
            "date_de_naissance": "2000-12-30",
            "casques": "/data/img/casques/sargeant.png",
            "photo": "/data/img/pilotes/sargeant.png"
        },
        {
            "prenom": "Valtteri",
            "nom": "Bottas",
            "numero_pilote": 77,
            "nombre_de_victoires": 10,
            "equipe": "Kick Sauber",
            "pays_origine": "Finland",
            "nb_podiums": 67,
            "points_totaux": 1797,
            "grands_prix_effectues": 224,
            "nombre_de_coupes_du_monde": 0,
            "meilleur_place": 1,
            "date_de_naissance": "1989-08-28",
            "casques": "/data/img/casques/bottas.png",
            "photo": "/data/img/pilotes/bottas.png"
        },
        {
            "prenom": "Pierre",
            "nom": "Gasly",
            "numero_pilote": 10,
            "nombre_de_victoires": 1,
            "equipe": "Alpine",
            "pays_origine": "France",
            "nb_podiums": 4,
            "points_totaux": 394,
            "grands_prix_effectues": 132,
            "nombre_de_coupes_du_monde": 0,
            "meilleur_place": 1,
            "date_de_naissance": "1996-02-07",
            "casques": "/data/img/casques/gasly.png",
            "photo": "/data/img/pilotes/gasly.png"
        }
    ]
}